MANIFEST.in
setup.py
src/cyburgee.scalapb.pants.egg-info/PKG-INFO
src/cyburgee.scalapb.pants.egg-info/SOURCES.txt
src/cyburgee.scalapb.pants.egg-info/dependency_links.txt
src/cyburgee.scalapb.pants.egg-info/top_level.txt
src/cyburgee.scalapb.pants.egg-info/zip-safe
src/scalapb/pants/__init__.py
src/scalapb/pants/register.py
src/scalapb/pants/targets/__init__.py
src/scalapb/pants/targets/scalapb_library.py
src/scalapb/pants/tasks/__init__.py
src/scalapb/pants/tasks/scalapb_gen.py