Metadata-Version: 1.1
Name: cyburgee.scalapb.pants
Version: 0.5.1
Summary: ScalaPB plugin for Pants
Home-page: https://github.com/cyburgee/scalapb-pants
Author: Collin Burger
Author-email: collin.e.burger@gmail.com
License: Apache License, Version 2.0
Platform: UNKNOWN
Classifier: Intended Audience :: Developers
Classifier: License :: OSI Approved :: Apache Software License
Classifier: Operating System :: OS Independent
Classifier: Programming Language :: Python
